bollinger_bands/__init__.py
bollinger_bands/calculations/__init__.py
bollinger_bands/calculations/bb.py
bollinger_bands/constants/__init__.py
bollinger_bands/constants/constants.py
bollinger_bands/core/__init__.py
bollinger_bands/core/bands.py
bollinger_bands/utilities/__init__.py
bollinger_bands/utilities/parser.py
bollinger_bands-0.1.4.dist-info/licenses/LICENSE
bollinger_bands-0.1.4.dist-info/METADATA
bollinger_bands-0.1.4.dist-info/WHEEL
bollinger_bands-0.1.4.dist-info/top_level.txt
bollinger_bands-0.1.4.dist-info/RECORD
