Metadata-Version: 2.4
Name: bollinger_bands
Version: 0.1.4
Summary: A Bollinger Band indicator built on top of financial_engine
Author-email: Raj Adhikari <adhikarirajj07@gmail.com>
License: Proprietary
Project-URL: GitHub, https://github.com/r-adhikari97
Project-URL: LinkedIn, https://www.linkedin.com/in/adhikari-raj/
Requires-Python: >=3.10
License-File: LICENSE
Requires-Dist: financial-engine
Dynamic: license-file
